{
  "generated_at": "2026-07-09T15:16:59.578857+09:00",
  "date_label": "7/9(목)",
  "articles": [
    {
      "title": "與 '선관위 개혁3법' 발의…위원장 상임화·사무총장 인사청문회 실시",
      "link": "https://n.news.naver.com/mnews/article/003/0014056854",
      "section": "100",
      "image": "images/article_01.png",
      "ok": true
    },
    {
      "title": "원 구성·보완수사권 평행선…기약없는 후반기 국회 정상화",
      "link": "https://n.news.naver.com/mnews/article/016/0002668054",
      "section": "100",
      "image": "images/article_02.png",
      "ok": true
    },
    {
      "title": "김정은, 김일성 32주기 맞아 금수산궁전 참배... 北 '독자 우상화'도 착착",
      "link": "https://n.news.naver.com/mnews/article/469/0000941084",
      "section": "100",
      "image": "images/article_03.png",
      "ok": true
    },
    {
      "title": "안철수 \"계엄 밤 한동훈이 먼저 당사 소집\"...한동훈 \"일시적\" 반박",
      "link": "https://n.news.naver.com/mnews/article/437/0000500289",
      "section": "100",
      "image": "images/article_04.png",
      "ok": true
    },
    {
      "title": "[단독] 이런데도 ‘보완수사권 폐지’ 밀어붙이는 與",
      "link": "https://n.news.naver.com/mnews/article/005/0001859812",
      "section": "100",
      "image": "images/article_05.png",
      "ok": true
    },
    {
      "title": "6월 아파트 분양가 또 역대 최고치",
      "link": "https://n.news.naver.com/mnews/article/005/0001859844",
      "section": "101",
      "image": "images/article_06.png",
      "ok": true
    },
    {
      "title": "5월 나라 살림 54조원 적자…중앙정부 채무 1345조원",
      "link": "https://n.news.naver.com/mnews/article/079/0004166538",
      "section": "101",
      "image": "images/article_07.png",
      "ok": true
    },
    {
      "title": "집값·증시 일제히 오르자… 7월 아파트 입주전망 대폭 상승",
      "link": "https://n.news.naver.com/mnews/article/469/0000941271",
      "section": "101",
      "image": "images/article_08.png",
      "ok": true
    },
    {
      "title": "솔리드웍스 CAD 왜 비싼가 했더니…대리점 담합으로 53% 인상",
      "link": "https://n.news.naver.com/mnews/article/138/0002233698",
      "section": "101",
      "image": "images/article_09.png",
      "ok": true
    },
    {
      "title": "중국 가기 전 마지막 한국여행…루이·후이, 전국 누빈다",
      "link": "https://n.news.naver.com/mnews/article/421/0009050024",
      "section": "101",
      "image": "images/article_10.png",
      "ok": true
    },
    {
      "title": "은평 빌라 화재 초등생 남매 희생…아버지 외출한 사이 참변",
      "link": "https://n.news.naver.com/mnews/article/003/0014056579",
      "section": "102",
      "image": "images/article_11.png",
      "ok": true
    },
    {
      "title": "‘세상 떠난 딸’ 비관하다… 분당 중식당 남편 독살 사건",
      "link": "https://n.news.naver.com/mnews/article/005/0001859918",
      "section": "102",
      "image": "images/article_12.png",
      "ok": true
    },
    {
      "title": "'5·18 비하' 배재고, 징계 재심 신청하지만…실효성 불투명",
      "link": "https://n.news.naver.com/mnews/article/015/0005307670",
      "section": "102",
      "image": "images/article_13.png",
      "ok": true
    },
    {
      "title": "'음료 테러 자작극 의혹' 정이한, 결국 구속",
      "link": "https://n.news.naver.com/mnews/article/055/0001370965",
      "section": "102",
      "image": "images/article_14.png",
      "ok": true
    },
    {
      "title": "김상욱 울산시장 \"울산 산업 AX 100억짜리 말고 조 단위 사업 필요\"",
      "link": "https://n.news.naver.com/mnews/article/014/0005546053",
      "section": "102",
      "image": "images/article_15.png",
      "ok": true
    },
    {
      "title": "트럼프 예고대로…이란 매체 “북동부 철도 교량 공격받았다”",
      "link": "https://n.news.naver.com/mnews/article/028/0002813319",
      "section": "104",
      "image": "images/article_16.png",
      "ok": true
    },
    {
      "title": "\"결혼식장 곳곳 대스타\" 경품은 샤넬백…'초호화' 현장",
      "link": "https://n.news.naver.com/mnews/article/055/0001370735",
      "section": "104",
      "image": "images/article_17.png",
      "ok": true
    },
    {
      "title": "미군, 연이틀 이란 공습…트럼프 \"다시 시작은 아니다…장기전 추구 안해\"",
      "link": "https://n.news.naver.com/mnews/article/082/0001388984",
      "section": "104",
      "image": "images/article_18.png",
      "ok": true
    },
    {
      "title": "中, 앤트로픽 '클로드 코드' 삭제 권고…AI 패권 갈등, 보안 이슈 비화",
      "link": "https://n.news.naver.com/mnews/article/586/0000133351",
      "section": "104",
      "image": "images/article_19.png",
      "ok": true
    },
    {
      "title": "트럼프 \"내가 이란 암살 리스트 1순위\"",
      "link": "https://n.news.naver.com/mnews/article/374/0000520739",
      "section": "104",
      "image": "images/article_20.png",
      "ok": true
    }
  ]
}