{
  "generated_at": "2026-07-22T08:41:54.937146+09:00",
  "window_start": "2026-07-21T22:00:00+09:00",
  "window_end": "2026-07-22T06:00:00+09:00",
  "date_label": "7/22(수)",
  "sectors": [
    {
      "key": "politics_main",
      "label": "정치 관련 주요기사",
      "queries": [
        "정치",
        "국회",
        "여야"
      ],
      "articles": [
        {
          "title": "[연합뉴스] '명태균 여론조사 대납 의혹' 오세훈 시장, 오늘 1심 선고",
          "link": "https://n.news.naver.com/article/001/0016207102",
          "pubDate": "Wed, 22 Jul 2026 06:00:00 +0900",
          "long_link": "https://n.news.naver.com/mnews/article/001/0016207102?sid=102"
        },
        {
          "title": "[서울경제] 오세훈 운명의 날…‘여론조사 비용 대납 의혹’ 오늘 1심 선고",
          "link": "https://n.news.naver.com/article/011/0004643754",
          "pubDate": "Wed, 22 Jul 2026 05:31:00 +0900",
          "long_link": "https://n.news.naver.com/mnews/article/011/0004643754?sid=102"
        },
        {
          "title": "[뉴스1] 오세훈 '명태균 여론조사비 대납' 1심 오늘 선고",
          "link": "https://n.news.naver.com/article/421/0009071466",
          "pubDate": "Wed, 22 Jul 2026 05:30:00 +0900",
          "long_link": "https://n.news.naver.com/mnews/article/421/0009071466?sid=102"
        },
        {
          "title": "[디지털타임스] ‘여론조사비 대납 의혹’ 오세훈, 22일 1심 선고…녹화 중계도 진행",
          "link": "https://n.news.naver.com/article/029/0003038158",
          "pubDate": "Wed, 22 Jul 2026 05:10:00 +0900",
          "long_link": "https://n.news.naver.com/mnews/article/029/0003038158?sid=102"
        },
        {
          "title": "[연합뉴스TV] '여론조사 대납 의혹' 오세훈…오늘 법원 첫 판단",
          "link": "https://n.news.naver.com/article/422/0000887462",
          "pubDate": "Wed, 22 Jul 2026 05:09:00 +0900",
          "long_link": "https://n.news.naver.com/mnews/article/422/0000887462?sid=102"
        },
        {
          "title": "[TV조선] '여론조사비 대납' 오세훈 오늘 1심 선고…구형은 징역 1년 6개월",
          "link": "https://n.news.naver.com/article/448/0000628394",
          "pubDate": "Wed, 22 Jul 2026 03:29:00 +0900",
          "long_link": "https://n.news.naver.com/mnews/article/448/0000628394?sid=102"
        },
        {
          "title": "[KBS] 오세훈 ‘여론조사비 대납’ 오늘 선고…징역 1년 6개월 구형",
          "link": "https://n.news.naver.com/article/056/0012222492",
          "pubDate": "Wed, 22 Jul 2026 01:03:00 +0900",
          "long_link": "https://n.news.naver.com/mnews/article/056/0012222492?sid=102"
        },
        {
          "title": "[YTN] '여론조사 대납' 오세훈 오늘 1심 선고...징역 1년 6개월 구형",
          "link": "https://n.news.naver.com/article/052/0002382665",
          "pubDate": "Wed, 22 Jul 2026 01:01:00 +0900",
          "long_link": "https://n.news.naver.com/mnews/article/052/0002382665?sid=102"
        }
      ]
    },
    {
      "key": "dp",
      "label": "더불어민주당 동정",
      "queries": [
        "더불어민주당"
      ],
      "articles": [
        {
          "title": "[한겨레] 우원식 “민주당, 양극화 토론 한번을 안 해…중산층·서민 정당 맞나”",
          "link": "https://n.news.naver.com/article/028/0002815160",
          "pubDate": "Wed, 22 Jul 2026 05:02:00 +0900",
          "long_link": "https://n.news.naver.com/mnews/article/028/0002815160?sid=100"
        },
        {
          "title": "[서울신문] 정청래 차량 파손에 ‘신천지 개입설’까지… 선 넘는 與전대",
          "link": "https://n.news.naver.com/article/081/0003663208",
          "pubDate": "Wed, 22 Jul 2026 05:01:00 +0900",
          "long_link": "https://n.news.naver.com/mnews/article/081/0003663208?sid=100"
        },
        {
          "title": "[노컷뉴스] 김민석은 왜 '신천지'를 언급할까…숨겨진 전략은",
          "link": "https://n.news.naver.com/article/079/0004170634",
          "pubDate": "Wed, 22 Jul 2026 05:01:00 +0900",
          "long_link": "https://n.news.naver.com/mnews/article/079/0004170634?sid=100"
        },
        {
          "title": "[뉴시스] 與 전대, 김민석·정청래 충돌 격화…'反明' 설전에 '4년 전 이 대통령 ...",
          "link": "https://n.news.naver.com/article/003/0014079777",
          "pubDate": "Wed, 22 Jul 2026 05:00:00 +0900",
          "long_link": "https://n.news.naver.com/mnews/article/003/0014079777?sid=100"
        },
        {
          "title": "[뉴시스] 오세훈 오늘 '여론조사비 대납 혐의' 1심 선고…구형 징역 1년6개월",
          "link": "https://n.news.naver.com/article/003/0014079773",
          "pubDate": "Wed, 22 Jul 2026 05:00:00 +0900",
          "long_link": "https://n.news.naver.com/mnews/article/003/0014079773?sid=102"
        }
      ]
    },
    {
      "key": "ppp",
      "label": "국민의힘 동정",
      "queries": [
        "국민의힘"
      ],
      "articles": [
        {
          "title": "[머니투데이] 오세훈, 여론조사 대납 1심 선고 '운명의 날'…구형은 '시장직 박탈형'",
          "link": "https://n.news.naver.com/article/008/0005388961",
          "pubDate": "Wed, 22 Jul 2026 05:01:00 +0900",
          "long_link": "https://n.news.naver.com/mnews/article/008/0005388961?sid=102"
        },
        {
          "title": "[디지털타임스] “배우자가 무슨 역할 했나”…우원식 해외출장 14회 모두 동행·82억 집...",
          "link": "https://n.news.naver.com/article/029/0003038151",
          "pubDate": "Wed, 22 Jul 2026 02:50:00 +0900",
          "long_link": "https://n.news.naver.com/mnews/article/029/0003038151?sid=100"
        },
        {
          "title": "[JIBS] \"노인 비하, 당게 한동훈 따라갈 수 없다\" 발언 장예찬 무혐의.. 張 \"검...",
          "link": "https://n.news.naver.com/article/661/0000080295",
          "pubDate": "Wed, 22 Jul 2026 00:20:00 +0900",
          "long_link": "https://n.news.naver.com/mnews/article/661/0000080295?sid=100"
        },
        {
          "title": "[더팩트] '장동혁 사퇴론' 동력 상실?…잠잠해진 진짜 이유는",
          "link": "https://n.news.naver.com/article/629/0000517842",
          "pubDate": "Wed, 22 Jul 2026 00:01:00 +0900",
          "long_link": "https://n.news.naver.com/mnews/article/629/0000517842?sid=100"
        },
        {
          "title": "[더팩트] '강경 징계' 역풍 기대한 한동훈?…국힘, '본보기 카드' 무게 두나",
          "link": "https://n.news.naver.com/article/629/0000517843",
          "pubDate": "Wed, 22 Jul 2026 00:01:00 +0900",
          "long_link": "https://n.news.naver.com/mnews/article/629/0000517843?sid=100"
        }
      ]
    },
    {
      "key": "economy",
      "label": "경제 동정",
      "queries": [
        "경제",
        "증권",
        "환율",
        "AI",
        "빅테크"
      ],
      "articles": [
        {
          "title": "[한국일보] 코스닥 역주행에 커지는 '상폐 공포'... 이재명 취임 전으로 회귀",
          "link": "https://n.news.naver.com/article/469/0000943610",
          "pubDate": "Wed, 22 Jul 2026 04:31:00 +0900",
          "long_link": "https://n.news.naver.com/mnews/article/469/0000943610?sid=101"
        },
        {
          "title": "[이데일리] [단독]'따릉이 정보유출'에도…서울시설공단 이사장 연임 논란",
          "link": "https://n.news.naver.com/article/018/0006334250",
          "pubDate": "Wed, 22 Jul 2026 05:52:00 +0900",
          "long_link": "https://n.news.naver.com/mnews/article/018/0006334250?sid=100"
        },
        {
          "title": "[동아일보] [단독]노벨상 교수 “AI發 생산성 향상, 고용 창출까진 시차… 충격 불...",
          "link": "https://n.news.naver.com/article/020/0003735595",
          "pubDate": "Wed, 22 Jul 2026 04:34:00 +0900",
          "long_link": "https://n.news.naver.com/mnews/article/020/0003735595?sid=102"
        },
        {
          "title": "[더팩트] [단독] \"김일성 품, 진정한 조국\"…조총련 의장 자서전 입수",
          "link": "https://n.news.naver.com/article/629/0000517840",
          "pubDate": "Wed, 22 Jul 2026 00:01:00 +0900",
          "long_link": "https://n.news.naver.com/mnews/article/629/0000517840?sid=100"
        },
        {
          "title": "[머니투데이] [광화문]이재명 정부의 부동산 클라이맥스",
          "link": "https://n.news.naver.com/article/008/0005388944",
          "pubDate": "Wed, 22 Jul 2026 04:15:00 +0900",
          "long_link": "https://n.news.naver.com/mnews/article/008/0005388944?sid=101"
        }
      ]
    }
  ]
}